vertex2tex/__init__.py
vertex2tex/config.py
vertex2tex/document.py
vertex2tex/excep.py
vertex2tex/v2t.py
vertex2tex/test/__init__.py
vertex2tex/test/test_compress.py
vertex2tex/test/test_tokenize.py
vertex2tex/test/test_translate.py
vertex2tex-0.3.4.dist-info/LICENSE
vertex2tex-0.3.4.dist-info/METADATA
vertex2tex-0.3.4.dist-info/WHEEL
vertex2tex-0.3.4.dist-info/top_level.txt
vertex2tex-0.3.4.dist-info/RECORD
